setup.py
cxio/__init__.py
cxio/aspect_element.py
cxio/cx2cx.py
cxio/cx_constants.py
cxio/cx_reader.py
cxio/cx_util.py
cxio/cx_writer.py
cxio/element.py
cxio/element_maker.py
cxio/ndex_cx_helper.py
cxio.egg-info/PKG-INFO
cxio.egg-info/SOURCES.txt
cxio.egg-info/dependency_links.txt
cxio.egg-info/requires.txt
cxio.egg-info/top_level.txt
test/test1.py