Metadata-Version: 1.1
Name: cxio
Version: 0.3.0
Summary: Utility to parse CX JSON streams
Home-page: https://github.com/idekerlab/cxio_python
Author: Christian Zmasek
Author-email: cmzmasek@ucsd.edu
License: MIT License
Keywords: data visualization,visualization,cytoscape,bioinformatics,graph,network
Platform: UNKNOWN
Classifier: Intended Audience :: Science/Research
Classifier: Intended Audience :: Developers
Classifier: Operating System :: OS Independent
Classifier: Development Status :: 3 - Alpha
Classifier: Programming Language :: Python :: 2.7
Classifier: Programming Language :: Python :: 3.4
Classifier: Programming Language :: Python :: 3.5
Classifier: License :: OSI Approved :: MIT License
Classifier: Topic :: Scientific/Engineering :: Bio-Informatics
Classifier: Topic :: Scientific/Engineering :: Information Analysis
Classifier: Topic :: Scientific/Engineering :: Visualization
